pyduinocoin/__init__.py
pyduinocoin/dict_obj.py
pyduinocoin/exceptions.py
pyduinocoin/pyduinocoin.py
pyduinocoin-1.0.5.dist-info/LICENSE
pyduinocoin-1.0.5.dist-info/METADATA
pyduinocoin-1.0.5.dist-info/WHEEL
pyduinocoin-1.0.5.dist-info/top_level.txt
pyduinocoin-1.0.5.dist-info/RECORD
