Metadata-Version: 2.1
Name: pyduinocoin
Version: 1.0.5
Summary: pyDuinoCoin is a simple python integration for the DuinoCoin REST API, that allows developers to communicate with DuinoCoin Master Server.
Home-page: https://github.com/backrndsource/pyduinocoin
Author: Sergio Contreras Agustí (backrndsource)
Author-email: backrndsource@gmail.com
License: UNKNOWN
Project-URL: Bug Tracker, https://github.com/backrndsource/pyduinocoin/issues
Keywords: DUCO,DuinoCoin,api-rest,python3,duino,duino-coin,api,client,REST,crypto,coin
Platform: UNKNOWN
Classifier: Development Status :: 5 - Production/Stable
Classifier: Intended Audience :: Developers
Classifier: Topic :: Software Development :: Libraries
Classifier: Programming Language :: Python
Classifier: Programming Language :: Python :: 3
Classifier: Programming Language :: Python :: 3.5
Classifier: Programming Language :: Python :: 3.6
Classifier: Programming Language :: Python :: 3.7
Classifier: Programming Language :: Python :: 3.8
Classifier: Programming Language :: Python :: 3.9
Classifier: License :: OSI Approved :: MIT License
Classifier: Operating System :: OS Independent
Requires-Python: >=3.5
License-File: LICENSE
